clavicle/__init__.py
clavicle/admin.py
clavicle/apps.py
clavicle/dbrouter.py
clavicle/migrations/0001_initial.py
clavicle/migrations/0002_auto_20231008_1125.py
clavicle/migrations/__init__.py
clavicle/models.py
clavicle/tests.py
clavicle/views.py
corpus_clavicle-0.1.1.dist-info/METADATA
corpus_clavicle-0.1.1.dist-info/WHEEL
corpus_clavicle-0.1.1.dist-info/RECORD
