Metadata-Version: 2.1
Name: corpus-clavicle
Version: 0.1.1
Summary: Total proteomics differential analysis models and auxilaries for Corpus
Author: Toan Phung
Author-email: toan.phung@proteo.info
Requires-Python: >=3.9,<4.0
Classifier: Programming Language :: Python :: 3
Classifier: Programming Language :: Python :: 3.9
Classifier: Programming Language :: Python :: 3.10
Classifier: Programming Language :: Python :: 3.11
Requires-Dist: django (>=4.2.6,<5.0.0)
Requires-Dist: django-postgres-extra (>=2.0.8,<3.0.0)
Requires-Dist: psycopg2 (>=2.9.9,<3.0.0)
